LICENSE
MANIFEST.in
README.rst
setup.py
tests.py
serialkiller/__init__.py
serialkiller/lib.py
serialkiller/sk_command.py
serialkiller/sk_server.py
serialkiller.egg-info/PKG-INFO
serialkiller.egg-info/SOURCES.txt
serialkiller.egg-info/dependency_links.txt
serialkiller.egg-info/entry_points.txt
serialkiller.egg-info/not-zip-safe
serialkiller.egg-info/requires.txt
serialkiller.egg-info/top_level.txt
serialkiller/server/static/js/d3.v3.min.js
serialkiller/server/templates/sensordatas.tpl
serialkiller/server/templates/sensorslist.tpl
serialkiller/sktypes/__init__.py
serialkiller/sktypes/skboolean.py
serialkiller/sktypes/skbyte.py
serialkiller/sktypes/skfloat.py
serialkiller/sktypes/skulong.py
serialkiller/sktypes/skushort.py