Metadata-Version: 1.1
Name: serialkiller
Version: 0.0.2
Summary: timeseries database with reduce system
Home-page: https://github.com/badele/serialkiller
Author: Bruno Adelé
Author-email: bruno@adele.im
License: GPL
Platform: UNKNOWN
Classifier: Programming Language :: Python
